opyoid/__init__.py
opyoid/exceptions.py
opyoid/frozen_target.py
opyoid/injection_context.py
opyoid/injection_state.py
opyoid/injector.py
opyoid/injector_options.py
opyoid/named.py
opyoid/provider.py
opyoid/provider_registry.py
opyoid/py.typed
opyoid/target.py
opyoid/utils.py
opyoid/bindings/__init__.py
opyoid/bindings/abstract_module.py
opyoid/bindings/binding.py
opyoid/bindings/binding_registry.py
opyoid/bindings/binding_to_provider_adapter.py
opyoid/bindings/condition.py
opyoid/bindings/module.py
opyoid/bindings/private_module.py
opyoid/bindings/registered_binding.py
opyoid/bindings/registered_multi_binding.py
opyoid/bindings/root_module.py
opyoid/bindings/class_binding/__init__.py
opyoid/bindings/class_binding/class_binding.py
opyoid/bindings/class_binding/class_binding_to_provider_adapter.py
opyoid/bindings/instance_binding/__init__.py
opyoid/bindings/instance_binding/from_instance_provider.py
opyoid/bindings/instance_binding/instance_binding.py
opyoid/bindings/instance_binding/instance_binding_to_provider_adapter.py
opyoid/bindings/multi_binding/__init__.py
opyoid/bindings/multi_binding/item_binding.py
opyoid/bindings/multi_binding/list_provider.py
opyoid/bindings/multi_binding/multi_binding.py
opyoid/bindings/multi_binding/multi_binding_to_provider_adapter.py
opyoid/bindings/provider_binding/__init__.py
opyoid/bindings/provider_binding/from_provider_provider.py
opyoid/bindings/provider_binding/provider_binding.py
opyoid/bindings/provider_binding/provider_binding_to_provider_adapter.py
opyoid/bindings/self_binding/__init__.py
opyoid/bindings/self_binding/callable_to_provider_adapter.py
opyoid/bindings/self_binding/from_callable_provider.py
opyoid/bindings/self_binding/self_binding.py
opyoid/bindings/self_binding/self_binding_to_provider_adapter.py
opyoid/conditions/__init__.py
opyoid/conditions/conditional_on_env_var.py
opyoid/conditions/env_var_condition.py
opyoid/providers/__init__.py
opyoid/providers/provider_creator.py
opyoid-3.0.4.dist-info/licenses/LICENSE.txt
opyoid-3.0.4.dist-info/METADATA
opyoid-3.0.4.dist-info/WHEEL
opyoid-3.0.4.dist-info/top_level.txt
opyoid-3.0.4.dist-info/RECORD
