Metadata-Version: 2.4
Name: opyoid
Version: 3.0.4
Summary: Dependency injection library
Author-email: Illuin Technology <contact@illuin.tech>
Maintainer-email: Illuin Technology <contact@illuin.tech>
Project-URL: Homepage, https://github.com/illuin-tech/opyoid
Project-URL: Bug Reports, https://github.com/illuin-tech/opyoid/issues
Project-URL: Source, https://github.com/illuin-tech/opyoid/
Platform: any
Classifier: Development Status :: 5 - Production/Stable
Classifier: Intended Audience :: Developers
Classifier: Operating System :: OS Independent
Classifier: License :: OSI Approved :: MIT License
Classifier: Programming Language :: Python
Classifier: Programming Language :: Python :: 3
Classifier: Programming Language :: Python :: 3 :: Only
Classifier: Programming Language :: Python :: 3.8
Classifier: Programming Language :: Python :: 3.9
Classifier: Programming Language :: Python :: 3.10
Classifier: Programming Language :: Python :: 3.11
Classifier: Topic :: Software Development :: Libraries
Classifier: Topic :: Software Development :: Libraries :: Python Modules
Classifier: Typing :: Typed
Requires-Python: >=3.9
License-File: LICENSE.txt
Requires-Dist: attrs<26.0.0,>=19.1.0
Provides-Extra: dev
Requires-Dist: black==25.11.0; extra == "dev"
Requires-Dist: build==1.3.0; extra == "dev"
Requires-Dist: mypy==1.19.1; extra == "dev"
Requires-Dist: pytest==8.4.2; extra == "dev"
Requires-Dist: pytest-cov==7.0.0; extra == "dev"
Requires-Dist: pylint==3.3.9; extra == "dev"
Requires-Dist: setuptools==80.9.0; extra == "dev"
Requires-Dist: twine==6.2.0; extra == "dev"
Requires-Dist: wheel==0.45.1; extra == "dev"
Dynamic: license-file
